gtracr/__init__.py
gtracr/trajectory.py
gtracr/utils.py
gtracr/version.py
gtracr/data/IGRF13.COF
gtracr/data/IGRF13.shc
gtracr/data/igrf13.json
gtracr/data/location_dict.pkl
gtracr/data/particle_dict.pkl
gtracr/lib/__init__.py
gtracr/lib/_libgtracr.cp37-win32.pyd
gtracr/lib/constants.py
gtracr/lib/igrf_utils.py
gtracr/lib/location.py
gtracr/lib/magnetic_field.py
gtracr/lib/particle.py
gtracr/lib/trajectory_tracer.py
gtracr/lib/trajectorypoint.py
gtracr/scripts/__init__.py
gtracr/scripts/cof_to_json.py
gtracr/scripts/set_locations.py
gtracr/scripts/set_particles.py
gtracr/tests/__init__.py
gtracr/tests/test_bfield.py
gtracr/tests/test_trajectories.py
gtracr-0.7.0.dist-info/LICENSE
gtracr-0.7.0.dist-info/METADATA
gtracr-0.7.0.dist-info/WHEEL
gtracr-0.7.0.dist-info/top_level.txt
gtracr-0.7.0.dist-info/RECORD
