Metadata-Version: 2.1
Name: gtracr
Version: 0.7.0
Summary: A GPU-based simulation that tracks cosmic rays from any location on Earth.
Home-page: https://github.com/kwat0308/gtracr
Author: Keito Watanabe
Author-email: k.wat8973@gmail.com
License: BSD 3-Clause License
Platform: UNKNOWN
Classifier: Programming Language :: Python
Classifier: Programming Language :: Python :: 3
Classifier: Topic :: Software Development
Classifier: Topic :: Scientific/Engineering
Classifier: Topic :: Scientific/Engineering :: Physics
Classifier: Intended Audience :: Science/Research
Classifier: Intended Audience :: Developers
Classifier: Development Status :: 4 - Beta
Classifier: Natural Language :: English
Classifier: License :: OSI Approved :: BSD License
Requires-Python: >=3.0
Provides-Extra: examples
